osqppurepy/__init__.py
osqppurepy/_osqp.py
osqppurepy/interface.py
tyba_osqp-0.6.1.dist-info/top_level.txt
tyba_osqp-0.6.1.dist-info/RECORD
tyba_osqp-0.6.1.dist-info/LICENSE
tyba_osqp-0.6.1.dist-info/METADATA
tyba_osqp-0.6.1.dist-info/WHEEL
osqp/__init__.py
osqp/utils.py
osqp/_osqp.cpython-38-aarch64-linux-gnu.so
osqp/interface.py
osqp/codegen/__init__.py
osqp/codegen/code_generator.py
osqp/codegen/utils.py
osqp/codegen/sources/include/types.h
osqp/codegen/sources/include/CMakeLists.txt
osqp/codegen/sources/include/util.h
osqp/codegen/sources/include/scaling.h
osqp/codegen/sources/include/constants.h
osqp/codegen/sources/include/error.h
osqp/codegen/sources/include/auxil.h
osqp/codegen/sources/include/qdldl_interface.h
osqp/codegen/sources/include/qdldl.h
osqp/codegen/sources/include/kkt.h
osqp/codegen/sources/include/proj.h
osqp/codegen/sources/include/osqp.h
osqp/codegen/sources/include/lin_alg.h
osqp/codegen/sources/include/qdldl_types.h
osqp/codegen/sources/include/glob_opts.h
osqp/codegen/sources/src/CMakeLists.txt
osqp/codegen/sources/src/kkt.c
osqp/codegen/sources/src/qdldl.c
osqp/codegen/sources/src/lin_alg.c
osqp/codegen/sources/src/osqp.c
osqp/codegen/sources/src/auxil.c
osqp/codegen/sources/src/qdldl_interface.c
osqp/codegen/sources/src/util.c
osqp/codegen/sources/src/proj.c
osqp/codegen/sources/src/error.c
osqp/codegen/sources/src/scaling.c
osqp/codegen/sources/configure/osqp_configure.h.in
osqp/codegen/sources/configure/qdldl_types.h.in
osqp/codegen/files_to_generate/setup.py
osqp/codegen/files_to_generate/CMakeLists.txt
osqp/codegen/files_to_generate/example.c
osqp/codegen/files_to_generate/emosqpmodule.c
osqp/tests/mkl_pardiso_test.py
osqp/tests/non_convex_test.py
osqp/tests/warm_start_test.py
osqp/tests/unconstrained_test.py
osqp/tests/__init__.py
osqp/tests/update_matrices_test.py
osqp/tests/feasibility_test.py
osqp/tests/codegen_vectors_test.py
osqp/tests/dual_infeasibility_test.py
osqp/tests/polishing_test.py
osqp/tests/primal_infeasibility_test.py
osqp/tests/basic_test.py
osqp/tests/codegen_matrices_test.py
