Metadata-Version: 2.1
Name: tyba-osqp
Version: 0.6.1
Summary: OSQP: The Operator Splitting QP Solver
Home-page: https://osqp.org/
Author: Bartolomeo Stellato, Goran Banjac
Author-email: bartolomeo.stellato@gmail.com
License: Apache 2.0
License-File: LICENSE
Requires-Dist: numpy (>=1.7)
Requires-Dist: scipy (>=0.13.2)
Requires-Dist: future
